MANIFEST.in
README.rst
setup.py
copyusb/__init__.py
copyusb.egg-info/PKG-INFO
copyusb.egg-info/SOURCES.txt
copyusb.egg-info/dependency_links.txt
copyusb.egg-info/not-zip-safe
copyusb.egg-info/top_level.txt