Metadata-Version: 1.1
Name: copyusb
Version: 1.1.0
Summary: Copy connected USB media device to current script directory.
Home-page: http://github.com/arsho/copyusb
Author: Ahmedur Rahman Shovon
Author-email: shovon.sylhet@gmail.com
License: MIT
Keywords: usb copy clone copier cloner drive
Platform: Ubuntu
Classifier: Development Status :: 3 - Alpha
Classifier: License :: OSI Approved :: MIT License
Classifier: Programming Language :: Python :: 3
Classifier: Topic :: Desktop Environment :: File Managers
